{
  "offsets": {
    "o_i10": 20.0,
    "o_i11": -30.0,
    "o_i12": 5.0,
    "o_i13": 5.0,
    "o_m20": 0.0,
    "o_m21": 10.0,
    "o_m22": 10.0,
    "o_m23": 10.0,
    "o_p40": 0.0,
    "o_p41": -15.0,
    "o_p42": 15.0,
    "o_p43": 5.0,
    "o_r30": -10.0,
    "o_r31": 0.0,
    "o_r32": 10.0,
    "o_r33": 10.0,
    "o_t00": -40.0,
    "o_t01": -80.0,
    "o_t02": 15.0,
    "o_t03": 10.0
  },
  "scales": {
    "i11": 1.5,
    "i12": 1.9,
    "i13": 2.1,
    "i_from_m": 0.8,
    "i_from_r": 1.9,
    "m20": 0.1,
    "m21": 1.2,
    "m22": 1.5,
    "m23": 1.6,
    "p40_curl": 0.0,
    "p40_spread": 0.2,
    "p41": 0.1,
    "p42": 1.5,
    "p43": 1.9,
    "r30": 0.7,
    "r31": 0.9,
    "r32": 1.5,
    "r33": 1.5,
    "t00_curl": 0.3,
    "t00_spread": 0.7,
    "t01": 0.5,
    "t02": 2.2,
    "t03": 1.4
  }
}